{
  "users": [
    {
      "id": 1,
      "name": "John Doe",
      "email": "johndoe@example.com",
      "age": 25
    },
    {
      "id": 2,
      "name": "Jane Doe",
      "email": "janedoe@example.com",
      "age": 29
    },
    {
      "id": 3,
      "name": "Alice Johnson",
      "email": "alicejohnson@example.com",
      "age": 31
    },
    {
      "id": 4,
      "name": "Bob Smith",
      "email": "bobsmith@example.com",
      "age": 27
    },
    {
      "id": 5,
      "name": "Linda Lee",
      "email": "lindalee@example.com",
      "age": 23
    },
    {
      "id": 6,
      "name": "David Davis",
      "email": "daviddavis@example.com",
      "age": 35
    },
    {
      "id": 7,
      "name": "Emily Anderson 1",
      "email": "emilyanderson@example.com",
      "age": 26
    },
    {
      "id": 8,
      "name": "George Wilson",
      "email": "georgewilson@example.com",
      "age": 33
    },
    {
      "id": 9,
      "name": "Karen Miller",
      "email": "karenmiller@example.com",
      "age": 28
    },
    {
      "id": 10,
      "name": "Tom Brown",
      "email": "tombrown@example.com",
      "age": 30
    },
    {
      "name": "Niyass",
      "email": "niyass@example.com",
      "age": "2",
      "id": 13
    },
    {
      "name": "folu",
      "email": "folu@example.com",
      "age": "42",
      "id": 15
    }
  ]
}